openapi_mcp_server/__init__.py
openapi_mcp_server/__main__.py
openapi_mcp_server/utils.py
openapi_mcp_server-0.2.1.dist-info/METADATA
openapi_mcp_server-0.2.1.dist-info/WHEEL
openapi_mcp_server-0.2.1.dist-info/entry_points.txt
openapi_mcp_server-0.2.1.dist-info/top_level.txt
openapi_mcp_server-0.2.1.dist-info/RECORD
