Metadata-Version: 2.2
Name: openapi_mcp_server
Version: 0.2.1
Summary: MCP Server For OpenAPI
Author-email: Rahul Kiran Gaddam <gaddam.rahul@gmail.com>
Project-URL: Homepage, https://github.com/rahgadda/openapi_mcp_server
Requires-Python: >=3.11
Requires-Dist: mcp[cli]>=1.4.1
Requires-Dist: pydantic>=2.10.6
Requires-Dist: python-dotenv>=1.0.1
Requires-Dist: requests>=2.32.3
